Workbook

Sheet Instructions
B2: Screen & Classify — Working Template
B3: Check scientific accuracy & currency; sort by crop, topic and content type
B5: Purpose
B6: • This is the working template for the Screen & Classify step: checking each inventoried item's scientific accuracy and currency, then sorting/classifying it by crop, topic and content type.
B7: • It follows on from the Content Inventory template — every item sourced there gets screened here before it is certified for the Kenya Advisory Knowledge Hub.
B9: How to Use This Workbook
B10: • Each group has its own tab: Crop, Livestock, Fisheries, Soil, and Pest & Disease.
B11: • One row = one content item (one source publication/brochure/guide).
B12: • The first data row on each tab is a worked EXAMPLE (greyed out) — reference only, do not edit. The Livestock tab's example is drawn from a real KALRO publication; see the 'Camel Calf Example' tab for its full section-level breakdown.
B13: • Gold-shaded cells are yours to complete. The ID column auto-numbers itself.
B14: • Use the filter arrows on the header row to sort or filter by Value Chain/Commodity, Advisory Domain/Topic, or Content Type.
B16: Screening Checks
... B22: Field Definitions
B23: Content Title | C23: Title of the source publication/brochure/guide.
B24: Publication ID / Source Link | C24: Unique publication ID and/or URL where the source can be found.
B25: Institution & Author(s) | C25: Originating institution and named author(s).
B26: Publish Date | C26: Date the source was published.
B27: Value Chain / Commodity | C27: Crop, livestock species, fish species or theme this item addresses.
B28: Advisory Domain / Topic | C28: The specific advisory topics covered (e.g. calving management, tick control).
B29: Content Type | C29: Production guide, protocol/SOP, factsheet, advisory bulletin, brochure, training manual, poster/infographic, video.
B30: Format | C30: The medium the content exists in (PDF, text, video, etc.).
B31: Production System | C31: Farming/production system the content applies to (e.g. pastoral, smallholder mixed farming).
B32: Target Users | C32: Who the advisory is written for (farmers, extension officers, CAHWs, etc.).
B33: Country / AEZ | C33: Geographic and agro-ecological applicability.
B34: Last Reviewed (Currency Check) | C34: Date the content was last checked for scientific currency.
... B40: Screening Notes / Escalation Guidance | C40: Reviewer notes, open questions, and who to escalate high-risk items to.
B42: Legend
B43: Fill this in | C43: Gold-shaded cells — enter your screening data here.
B44: Example row | C44: Worked example — reference only, do not edit.

Sheet Crop
B1: Screen & Classify — Crop
B2: Screen & classify crop advisory content — production guides, agronomy, variety information
B3: Check scientific accuracy & currency, then sort/classify by crop, topic and content type. Gold-shaded cells are yours to complete. Dropdown columns are marked in the header. The ID column fills itself in. Use the filter arrows on the header row to sort by any field.
B5: ID | C5: Content Title | D5: Publication ID / Source Link | E5: Institution & Author(s) | F5: Publish Date | G5: Value Chain / Commodity | H5: Advisory Domain / Topic | I5: Content Type | J5: Format | K5: Production System | L5: Target Users | M5: Country / AEZ | N5: Last Reviewed (Currency Check) | O5: Currency Status | P5: Scientific Accuracy Check | Q5: Validation Status | R5: Risk Level | S5: Quality Flag | T5: Screening Notes / Escalation Guidance
B6: CROP-EX | C6: Maize (Zea mays) Production Guide - Highland Zones | D6: KALRO-CROP-2024-011 | E6: KALRO Katumani / J. Mwangi | F6: 2024-03-15 | G6: Maize | H6: Production guide; agronomy; variety selection | I6: Production Guide | J6: PDF | K6: Smallholder mixed farming | L6: Smallholder farmers, extension officers | M6: Kenya - Highland zones | N6: 2024-03-15 | O6: Current | P6: Verified | Q6: source_validated | R6: Low | S6: Ready to Certify | T6: Currency check needed against 2026 seed catalogue before certification.
B7: MAIZE-1 | C7: Farmers’ Extension Handbook Cereals and Pulses | E7: Kenya Agricultural and Livestock Research Organization | F7: 44287 | G7: Maize | I7: Training Manual | J7: PDF | L7: Farmers
B8: MAIZE-2 | C8: Maize smut (Common Smut) | E8: Kiritai S.Kagai K. Ngigi B. Mulaa M. | G8: Maize | H8: Plant Health | I8: Factsheet | J8: PDF | L8: Farmers
B9: MAIZE-3 | C9: Maize Lethal Necrosis Disease on Maize | E9: Gekone M., Otipa M., Kamau R. | G9: Maize | H9: Plant Health | I9: Factsheet | J9: PDF | L9: Farmers
B10: MAIZE-4 | C10: Phosphorus deficiency in Maize | E10: Kiritai S., Kagai K., Mulaa M., Kilalo D., Wendot P., Kiige P., Otipa M. | G10: Maize | H10: Plant Health | I10: Factsheet | J10: PDF | L10: Farmers
B11: MAIZE-5 | C11: Maize Stem Borer | E11: Mulaa M., Oronje M.L., Otipa M., Ringera E.K. | G11: Maize | H11: Plant Health | I11: Factsheet | J11: PDF | L11: Farmers
B12: MAIZE-6 | C12: Maize production training and extension manual | E12: Kenya Agricultural and Livestock Research Organization | F12: 42377 | G12: Maize | I12: Training Manual | J12: PDF | L12: Farmers
B13: MAIZE-7 | C13: Options for Striga management in Kenya | E13: Esilaba A.O. | F13: 38795 | G13: Maize | H13: Plant Health | I13: Factsheet | J13: PDF | L13: Farmers
B14: MAIZE-8 | C14: Harmonized Fertilizer Recommendations For Optimal Maize Production In Kenya | E14: Mangale N., Muriuki A., Kathuku-Gitonga A.N. and Mutegi J.K. | F14: 42644 | G14: Maize | I14: Production Guide | J14: PDF | L14: Farmers
B15: MAIZE-9 | C15: Maize Production Trainng and Extension Manual | D15: Library | E15: Kenya Agricultural and Livestock Research Organization | G15: Maize | I15: Training Manual | J15: PDF | L15: Farmers
B16: MAIZE-10 | C16: Technology, Innovations and Management Practices for Maize Volume II | D16: https://navcdp.kalro.org/docs/timps_2025/MAIZE%20TIMPS%20Volume-1%20for%20Upload.pdf | E16: KALRO/Musila R.N., et al. (2022) | G16: Maize | I16: Training Manual | J16: PDF | L16: Farmers
B17: MAIZE-11 | C17: Technology, Innovations and Management Practices for Maize Volume II | D17: https://navcdp.kalro.org/docs/timps_2025/MAIZE%20TIMPS%20Volume%202%20for%20upload.pdf | E17: Kenya Agricultural and Livestock Research Organization | G17: Maize | I17: Training Manual | J17: PDF | L17: Farmers
B18: MAIZE-12 | C18: Maize Trainer of Trainers’ Manual | D18: Library | E18: Karanja J. K., Otipa M., Esilaba A. O., Nyongesa D., Okoti M., Mutuma E., Kathuku-Gitonga A.N., Too A., Mutisya D., Njunie M.,. Muli B & Wasilwa L. | G18: Maize | I18: Training Manual | J18: PDF | L18: Farmers
B19: MAIZE-13 | C19: Your Feed Shortage Problem: Use Maize Forage | D19: Library | E19: Kenya Agricultural and Livestock Research Organization | G19: Maize | I19: Factsheet | J19: PDF | L19: Farmers
B20: MAIZE-14 | C20: Maize Training Manual | D20: https://www.kalro.org/navcdp/index.php/information-resoures/publications/training-manuals23 | E20: KALRO-NAVCDP | F20: Not stated | G20: Maize | H20: Good agricultural practices; climate-smart agriculture; agronomy | I20: Training manual | J20: PDF | K20: Smallholder rainfed/commercial | L20: Farmers; extension officers; lead farmers; service providers
B21: MAIZE-15 | C21: Maize Extension and Training Manual | D21: https://kalroerepository.kalro.org/handle/123456789/13957 | E21: KALRO; Karanja J.K.; Mwathi J.W.; Ooro P.A.; Esilaba A.O.; Nyongesa D.; Okoti M.; Githunguri C.; Miriti J.; Otipa M.; Nassiuma E.; Too A.; Kamidi M.; Wanjekeche E. | F21: 2019-04 | G21: Maize | H21: Agronomy; varieties; production; extension | I21: Extension manual | J21: PDF | K21: Rainfed; smallholder | L21: Extension officers; farmers; service providers
B22: MAIZE-16 | C22: KALRO-KCEP Maize Training and Extension Manual | D22: https://kalroerepository.kalro.org/handle/123456789/13966 | E22: KALRO-KCEP | F22: 2016-04 | G22: Maize | H22: Varieties; field operations; seed; production | I22: Training and extension manual | J22: PDF | K22: Rainfed; smallholder/commercial | L22: Farmers; extension officers; trainers
B23: MAIZE-17 | C23: Maize Trainer of Trainers’ Manual | D23: https://kalroerepository.kalro.org/handle/123456789/13956 | E23: KALRO; Karanja J.K.; Otipa M.; Esilaba A.O.; Nyongesa D.; Okoti M.; Mutuma E.; Kathuku-Gitonga A.N.; Too A.; Mutisya D.; Njunie M.; Muli B.; Wasilwa L. | F23: 2019-04 | G23: Maize | H23: Training methods; soil fertility; maize production | I23: ToT manual | J23: PDF | K23: Smallholder; rainfed | L23: Trainers; extension officers; lead farmers
B24: MAIZE-18 | C24: Solve Your Feed Shortage Problem: Use Maize Forage | D24: https://www.kalro.org/information-resources/information-brochures/ | E24: KALRO | F24: 2021 (site archive date) | G24: Maize | H24: Maize forage; livestock feed; fodder conservation | I24: Brochure | J24: PDF | K24: Mixed crop-livestock | L24: Dairy/livestock farmers; extension officers
B25: MAIZE-19 | C25: How to Control Maize Stalk Borer | D25: https://www.kalro.org/information-resources/information-brochures/ | E25: KALRO | F25: 2021 (site archive date) | G25: Maize | H25: Pest management; crop protection | I25: Extension brochure | J25: PDF | K25: Smallholder maize | L25: Farmers; extension officers
B26: MAIZE-20 | C26: Maize Good Agricultural Practices | D26: https://keep.kalro.org/good-agricultural-practices/Maize | E26: KALRO Kenya Digital Agriculture Platform | F26: Not stated | G26: Maize | H26: Site selection; land preparation; varieties; planting; crop health; post-harvest | I26: Digital learning resource | J26: Web | K26: Rainfed; smallholder/commercial | L26: Farmers; extension officers; agribusiness advisers
B27: MAIZE-21 | C27: KALRO GAPS – Maize and Bean Intercrop / Maize GAPs | D27: https://www.kalro.org/navcdp/index.php/information-resoures/mobile-apps | E27: KALRO-NAVCDP | F27: Not stated | G27: Maize | H27: Good agricultural practices; intercrop management | I27: Mobile learning application | J27: Mobile app | K27: Smallholder; rainfed | L27: Farmers; extension officers
B28: MAIZE-22 | C28: Multilocation Evaluation for Yield and Yield Related Traits in Three-Way Cross Maize Hybrids in Kenya | D28: https://www.kalro.org/information-resources/publications/ | E28: KALRO | F28: 2021-09-10 | G28: Maize | H28: Variety evaluation; yield; maize breeding | I28: Research/manual resource | J28: PDF/Web | K28: Rainfed; breeding trials | L28: Researchers; breeders; extension officers

Sheet Maize
B1: Maize Value Chain
B3: MAIZE ADVISORY
B4: Disclaimer: This resource provides general advisory guidance from a KALRO brochure. Farmer-facing recommendations should be localized and technically reviewed before AI delivery.
B5: # | C5: Section Header | D5: Content Summary | E5: Pages | F5: Content Warnings | G5: Content Tags | H5: Status
B6: 1 | C6: Maize production in Kenya | D6: Maize is a staple food in Kenya, accounting for an average production of 4.4 million tons for the period 2010 to 2013 (FAO, 2015). It contributes to about 65% of daily per capita cereal consumption and serves as a subsistence and commercial crop grown on an estimated 1.4 million hectares. Maize production accounts for more than 20% of the total agricultural production and 25% of agricultural employment in the country. It is an important source of carbohydrate, protein, iron, vitamin B, and minerals. Maize products include baked, roasted, and boiled fresh maize on the cob, porridge, pastes, beer, starch, oil, and livestock feed from by-products of fresh and dry maize grain. | E6: MAIZE-14 | F6: Verify site-specific production data for your region, monitor market prices for best-selling time, ensure proper storage to reduce 30% post-harvest losses, Climate change affects production patterns, diversify maize products for better income | G6: staple food, cereal consumption, subsistence crop, commercial crop, carbohydrate source, livestock feed | H6: Validated
B7: 2 | C7: Ecological requirement practices (Maize) | D7: Maize is well adapted to diverse climates and hence has wide-ranging maturities from 90 to 210 days, nutritive value, and tolerance/resistance to pests and diseases. In Kenya, maize is widely adapted to soils from the higher-rainfall uplands to the lowland areas. | E7: MAIZE-14 | F7: Match variety maturity to your specific agro-ecological zone, Consider local pest and disease pressure when selecting varieties, Soil type varies greatly - test before planting, Climate variability affects adaptation, Consult extension officer for site-specific advice | G7: climate adaptation, maturity range, nutritive value, pest resistance, disease tolerance, wide adaptation | H7: Validated
B8: 3 | C8: Altitude (Maize) | D8: Maize is grown at all altitudes ranging from zero metres above sea level (masl) at the Coast to more than 2,000 m.a.s.l of the highlands. | E8: MAIZE-14 | F8: Select varieties suited to your specific altitude, Higher altitudes require longer-maturing varieties, Coastal areas need heat-tolerant varieties, Temperature decreases with altitude affecting growth, Consult variety recommendations for your altitude zone | G8: sea level, altitude range, coastal lowlands, highlands, variety adaptation, temperature gradient | H8: Validated
B9: 4 | C9: Rainfall (Maize) | D9: Maize can grow and yield with as little as 250 mm but prefers 500 to 1200 mm as the optimal range. Depending on soil type and stored soil moisture, crop failure would be expected if less than 250 mm of rain were received for the crop. The rainfall should be fairly distributed during the growing period. For higher yields, the crop should receive enough rainfall during the first five weeks after sowing and at flowering time. Otherwise, moisture stress at flowering time interferes with pollination and drastically lowers the yields. | E9: MAIZE-14 | F9: Less than 250mm rainfall risks complete crop failure, Moisture stress at flowering causes severe yield reduction, Rainfall distribution more important than total amount, Consider drought-tolerant varieties in low rainfall areas, Supplementary irrigation may be needed in dry spells | G9: rainfall requirement, optimal range, moisture stress, pollination, flowering stage, crop failure risk | H9: Validated
B10: 5 | C10: Soil type (Maize) | D10: In Kenya, maize is grown on a wide range of soil types. Maize is also grown on lowland soils that are hard-setting, poorly structured, and low in nutrient levels due to leaching. Yields on these soils are very low, and maize production is considered uneconomical. The average soils for growing maize should be well drained, well aerated, deep and warm. The best soils for growing maize are silt loam with sufficient nutrients and a pH range of 5.5-6.8. Waterlogged soils should be avoided because if maize stands in water for more than two days, it withers and dies off. Soils should be routinely analyzed for nutrients. | E10: MAIZE-14 | F10: Avoid waterlogged soils - maize dies after 2 days in water, Conduct soil analysis before planting, Maintain soil pH between 5.5-6.8 for optimal growth, Lowland soils may be uneconomical for maize, Add organic matter to improve soil structure | G10: silt loam, soil pH, waterlogging, drainage, soil analysis, nutrient management | H10: Validated
B11: 6 | C11: Temperature (Maize) | D11: The optimum temperature for maize growth and development is 18 to 32 °C, with temperatures of 35 °C and above considered inhibitory, as it exposes the crop to much respiration, while cold conditions at high altitude will extend the life cycle, resulting in lower yields. However, through practising reduced tillage, maintaining ground cover or applying crop residues such as pulse straw, the impact of drought can be greatly reduced by lowering soil temperature and surface evaporation. | E11: MAIZE-14 | F11: Temperatures above 35°C reduce yields, Cold conditions extend maturity period, Use crop residues to moderate soil temperature, Mulching reduces heat stress on plants, Select heat-tolerant varieties for hot areas | G11: temperature range, heat stress, cold stress, crop residues, mulching, reduced tillage | H11: Validated
B12: 7 | C12: MAIZE AGRONOMIC PRACTICES - Varietal selection (Maize) | D12: The choice of appropriate maize varieties for a given location is very important because every variety has been extensively tested and recommended based on climatic conditions, soil type, yield potential, tolerance/resistance to pests and diseases, or maturity period, among others. | E12: MAIZE-14 | F12: Match variety to your specific agro-ecological zone, Consider pest and disease resistance, Check maturity period matches growing season, Consult extension officer for variety recommendations, Test new varieties on small plots first | G12: variety selection, agro-ecological zone, yield potential, disease tolerance, pest resistance, maturity period | H12: Validated
B13: 8 | C13: Open-pollinated variety (OPV) (Maize) | D13: These are stabilised varieties in which farmers do not need new seed each season. If farmers follow proper selection procedures, they can use their seeds selected from their harvests up to three seasons, after which they can buy fresh seeds from seed stockists. However, yields of OPV are lower than hybrids. | E13: MAIZE-14 | F13: OPV yields are lower than hybrids, Seed can be saved for max 3 seasons only, Proper selection procedures are essential, Yield declines with recycling beyond 3 seasons. Buy fresh seed from certified stockists | G13: open-pollinated variety, seed saving, three seasons, yield potential, seed selection, stockists | H13: Validated
B14: 9 | C14: Hybrid (Maize) | D14: Hybrids yield higher than OPVs. Farmers can choose to save their seeds for the next planting. However, as with all hybrid maize seeds, yield is reduced with recycling farm-saved seeds. It is good practice to plant new seed each season/year to ensure a consistently good harvest. | E14: MAIZE-14 | F14: Hybrid seed must be bought fresh each season. Recycled hybrid seed gives poor yields, Higher yield potential requires good management. More expensive seed but higher returns, Do not save seed from hybrid varieties | G14: hybrid maize, higher yield, fresh seed, season planting, consistent harvest, seed cost | H14: Validated
B15: 10 | C15: Land preparation (Maize) | D15: Good land preparation is very important as it enhances yield, controls crop diseases, and prevents pest invasion. There are three main techniques to carry out tillage practice: 1. Conventional tillage - use of mechanical farm implements for land preparation involving ploughing and harrowing using mouldboard plough, disc plough, subsoil plough, chisel plough, or plough powered by tractor or draft animals like oxen. 2. Minimum tillage - use of cutlass to slash weeds and vegetation regrowth; little manipulation with hoe and rake; stubble used as mulching material. 3. Zero tillage - opening narrow strip 2-3 cm wide or hole for seed; weeds controlled with herbicides; crop planted directly without tilling or ploughing. | E15: MAIZE-14 | F15: Improper land preparation increases erosion risk, Conventional tillage is costly (KES 4,500/acre), Zero tillage requires herbicides, Minimum tillage needs crop residues for mulching, Timely preparation critical for planting | G15: tillage practice, conventional tillage, minimum tillage, zero tillage, ploughing, harrowing | H15: Validated
B16: 11 | C16: Soil fertility management (Maize) | D16: Soil fertility can be managed through several strategies, including organic fertilizers/manures and inorganic or chemical fertilizers. Farmyard manure (FYM) can be applied either alone at a rate of 5 tons per acre. When FYM is used in combination with inorganic fertilizers half the recommended rates should be applied. Fertilizer recommendations are based on different agro-ecological zones and soil types. The main fertilizers used are (DAP, 23:23:0, 20:20:0, 17:17:17, Mavuno (Planting and topdressing) CAN, Urea, etc. | E16: MAIZE-14 | F16: Fertilizer rates vary by zone - follow local recommendations, Over-application pollutes environment and wastes money, FYM application (5 tons/acre) requires planning, Combine organic and inorganic for best results, Soil testing before fertilizer application essential | G16: organic fertilizer, inorganic fertilizer, farmyard manure, fertilizer rates, agro-ecological zone, soil fertility | H16: Validated
B17: 12 | C17: Management of acid soils (Maize) | D17: Liming is recommended for acidic soils. Soil liming recommendations: Application of lime at 6tha-1 will require another application after 3 years for those practicing continuous cropping or after six cropping seasons. Application of lime at 4tha-1 will require another application after 2.5 years or after five cropping seasons. Application of lime at 2tha-1 will require reapplication every two years for those who practice continuous cropping or after four cropping seasons. | E17: MAIZE-14 | F17: Test soil pH before applying lime, Lime rates depend on soil acidity level, Reapplication timing depends on application rate, Continuous cropping requires more frequent liming, Apply lime 2-3 months before planting for best results | G17: acid soils, liming, soil pH, application rate, reapplication timing, continuous cropping | H17: Validated
... B516: 511 | C516: Markets and Marketing for Cereals and Legumes - Maize | D516: Market: place where buyers and sellers meet to exchange goods/services. Marketing: process bridging producers and consumers; involves finding consumer wants and supplying at a profit. Organized farming reduces storage/transportation costs; central management at aggregation centres; quality checks/grading; bargaining advantage. | E516: MAIZE-1 | F516: Access to markets, price volatility, quality standards, storage costs. | G516: Market, Marketing, Aggregation, Bargaining, Quality Checks | H516: Validated

Sheet Summary
B2: Screening Summary (live count)
B3: Updates automatically as each group screens and classifies its items.
B5: Group | C5: Total Items | D5: Ready to Certify | E5: Needs Review | F5: Needs Update | G5: High Risk
B6: Crop | C6: =COUNTA(Crop!C7:C27) -> 21 | D6: =COUNTIF(Crop!S7:S27,"Ready to Certify") -> 0 | E6: =COUNTIF(Crop!S7:S27,"Needs Review") -> 0 | F6: =COUNTIF(Crop!S7:S27,"Needs Update") -> 0 | G6: =COUNTIF(Crop!R7:R27,"High") -> 0
B7: Livestock | C7: =COUNTA(#REF!) -> 1 | D7: =COUNTIF(#REF!,"Ready to Certify") -> #REF! | E7: =COUNTIF(#REF!,"Needs Review") -> #REF! | F7: =COUNTIF(#REF!,"Needs Update") -> #REF! | G7: =COUNTIF(#REF!,"High") -> #REF!
B8: Fisheries | C8: =COUNTA(#REF!) -> 1 | D8: =COUNTIF(#REF!,"Ready to Certify") -> #REF! | E8: =COUNTIF(#REF!,"Needs Review") -> #REF! | F8: =COUNTIF(#REF!,"Needs Update") -> #REF! | G8: =COUNTIF(#REF!,"High") -> #REF!
B9: Soil | C9: =COUNTA(#REF!) -> 1 | D9: =COUNTIF(#REF!,"Ready to Certify") -> #REF! | E9: =COUNTIF(#REF!,"Needs Review") -> #REF! | F9: =COUNTIF(#REF!,"Needs Update") -> #REF! | G9: =COUNTIF(#REF!,"High") -> #REF!
B10: Pest & Disease | C10: =COUNTA(#REF!) -> 1 | D10: =COUNTIF(#REF!,"Ready to Certify") -> #REF! | E10: =COUNTIF(#REF!,"Needs Review") -> #REF! | F10: =COUNTIF(#REF!,"Needs Update") -> #REF! | G10: =COUNTIF(#REF!,"High") -> #REF!
B11: TOTAL | C11: =SUM(C6:C10) -> 25 | D11: =SUM(D6:D10) -> #REF! | E11: =SUM(E6:E10) -> #REF! | F11: =SUM(F6:F10) -> #REF! | G11: =SUM(G6:G10) -> #REF!
