Workbook

Sheet Instructions
B2: Screen & Classify — Working Template
B3: Check scientific accuracy & currency; sort by crop, topic and content type
B5: Purpose
B6: • This is the working template for the Screen & Classify step: checking each inventoried item's scientific accuracy and currency, then sorting/classifying it by crop, topic and content type.
B7: • It follows on from the Content Inventory template — every item sourced there gets screened here before it is certified for the Kenya Advisory Knowledge Hub.
B9: How to Use This Workbook
B10: • Each group has its own tab: Crop, Livestock, Fisheries, Soil, and Pest & Disease.
B11: • One row = one content item (one source publication/brochure/guide).
B12: • The first data row on each tab is a worked EXAMPLE (greyed out) — reference only, do not edit. The Livestock tab's example is drawn from a real KALRO publication; see the 'Camel Calf Example' tab for its full section-level breakdown.
B13: • Gold-shaded cells are yours to complete. The ID column auto-numbers itself.
B14: • Use the filter arrows on the header row to sort or filter by Value Chain/Commodity, Advisory Domain/Topic, or Content Type.
B16: Screening Checks
... B22: Field Definitions
B23: Content Title | C23: Title of the source publication/brochure/guide.
B24: Publication ID / Source Link | C24: Unique publication ID and/or URL where the source can be found.
B25: Institution & Author(s) | C25: Originating institution and named author(s).
B26: Publish Date | C26: Date the source was published.
B27: Value Chain / Commodity | C27: Crop, livestock species, fish species or theme this item addresses.
B28: Advisory Domain / Topic | C28: The specific advisory topics covered (e.g. calving management, tick control).
B29: Content Type | C29: Production guide, protocol/SOP, factsheet, advisory bulletin, brochure, training manual, poster/infographic, video.
B30: Format | C30: The medium the content exists in (PDF, text, video, etc.).
B31: Production System | C31: Farming/production system the content applies to (e.g. pastoral, smallholder mixed farming).
B32: Target Users | C32: Who the advisory is written for (farmers, extension officers, CAHWs, etc.).
B33: Country / AEZ | C33: Geographic and agro-ecological applicability.
B34: Last Reviewed (Currency Check) | C34: Date the content was last checked for scientific currency.
... B40: Screening Notes / Escalation Guidance | C40: Reviewer notes, open questions, and who to escalate high-risk items to.
B42: Legend
B43: Fill this in | C43: Gold-shaded cells — enter your screening data here.
B44: Example row | C44: Worked example — reference only, do not edit.

Sheet Crop
B1: Screen & Classify — Crop
B2: Screen & classify crop advisory content — production guides, agronomy, variety information
B3: Check scientific accuracy & currency, then sort/classify by crop, topic and content type. Gold-shaded cells are yours to complete. Dropdown columns are marked in the header. The ID column fills itself in. Use the filter arrows on the header row to sort by any field.
B5: ID | C5: Content Title | D5: Publication ID / Source Link | E5: Institution & Author(s) | F5: Publish Date | G5: Value Chain / Commodity | H5: Advisory Domain / Topic | I5: Content Type | J5: Format | K5: Production System | L5: Target Users | M5: Country / AEZ | N5: Last Reviewed (Currency Check) | O5: Currency Status | P5: Scientific Accuracy Check | Q5: Validation Status | R5: Risk Level | S5: Quality Flag | T5: Screening Notes / Escalation Guidance
B6: CROP-EX | C6: Maize (Zea mays) Production Guide - Highland Zones | D6: KALRO-CROP-2024-011 | E6: KALRO Katumani / J. Mwangi | F6: 2024-03-15 | G6: Maize | H6: Production guide; agronomy; variety selection | I6: Production Guide | J6: PDF | K6: Smallholder mixed farming | L6: Smallholder farmers, extension officers | M6: Kenya - Highland zones | N6: 2024-03-15 | O6: Current | P6: Verified | Q6: source_validated | R6: Low | S6: Ready to Certify | T6: Currency check needed against 2026 seed catalogue before certification.
B7: CASSAVA-1 | C7: Technology, Innovations and Management Practices for Cassava | D7: https://navcdp.kalro.org/docs/kcsap/Cassava%20Aug2019-Munga.pdf | E7: Kenya Agricultural and Livestock Research Organization | G7: Cassava | I7: Training Manual | J7: PDF | L7: Farmers
B8: CASSAVA4 | C8: Cassava Training Manual | D8: https://www.kalro.org/navcdp/index.php/information-resoures/publications/training-manuals23 | E8: KALRO-NAVCDP | F8: Not stated | G8: Cassava | H8: Climate-smart cassava production; agronomy; varieties | I8: Training manual | J8: PDF | K8: Smallholder; rainfed | L8: Farmers; extension officers; trainers
B9: CASSAVA-5 | C9: Cassava Climate-Smart Agricultural Technologies Training Manual | D9: https://keep.kalro.org/appfiles/media/vc_files/cassava-8-12-20.pdf | E9: KALRO; climate-smart agriculture programme | F9: Not stated | G9: Cassava | H9: Climate change; FFBS; varieties; clean seed; agronomic practices | I9: Training manual | J9: PDF | K9: Climate-smart; rainfed | L9: Trainers; extension officers; lead farmers; farmers
B10: CASSAVA-6 | C10: Cassava Good Agricultural Practices | D10: https://keep.kalro.org/good-agricultural-practices/Cassava | E10: KALRO Kenya Digital Agriculture Platform | F10: Not stated | G10: Cassava | H10: Varieties; site selection; land preparation; planting; crop management | I10: Digital learning resource | J10: Web | K10: Smallholder; rainfed | L10: Farmers; extension officers
B11: CASSAVA-8 | C11: KALRO New Cassava Varieties | D11: https://www.kalro.org/navcdp/index.php/information-resoures/mobile-apps | E11: KALRO-NAVCDP | F11: Not stated | G11: Cassava | H11: Improved varieties; varietal selection | I11: Mobile learning application | J11: Mobile app | K11: Smallholder; climate-smart | L11: Farmers; extension officers; agro-dealers

Sheet Cassava
A2: Cassava
A3: # | B3: Section Header | C3: Content Summary | D3: Pages | E3: Content Warnings | F3: Content Tags | G3: Status
A4: 1 | B4: Cassava variety MM95/0183 (Cassava) | C4: Mid-maturing variety ready for harvest from 8–12 months after planting, medium/high yielding 25–62 t/ha, sweet tasting (low cyanide content 7.9 mg/100 g). Tolerant to CBSD, CBB, CMD, CMB and CGM with 26% dry matter. Performs well at 800–1200 mm rainfall, altitudes of 800–1500 m.a.s.l. and temperatures of 14–30 °C. | D4: CASSAVA-1 | E4: Requires well-drained sandy loam soils, Optimal rainfall 800–1200 mm annually, Certified seed availability limited, Monitor for emerging disease strains, Best for Western and Coastal Kenya regions | F4: mid-maturing, high yielding, low cyanide, disease tolerant, 26% dry matter, sweet tasting | G4: Validated
A5: 2 | B5: Cassava variety Katsuhanzala (990132) (Cassava) | C5: Yields 36.7 t/ha, matures in 8–10 months, resistant to CMD and tolerant to CBSD, CGM and CMB with cream root flesh colour. Dry matter 29%. Adapted to a wide range of agroecological zones from coastal lowlands to highland coffee zones (200–1500 m.a.s.l.). | D5: CASSAVA-1 | E5: Adapted to wide altitude range (200–1500 m.a.s.l.), Requires well-drained sandy loam soils, Rainfall 500–1000 mm annually, Monitor for pest resistance durability, Seed availability may be limited in some regions | F5: CMD resistant, CBSD tolerant, cream flesh, 29% dry matter, wide adaptation, moderate yielder | G5: Validated
A6: 3 | B6: Cassava variety KME-3 (Cassava) | C6: Drought tolerant, medium yielder (40 t/ha), resistant to CMD, early maturing variety with low cyanogenic potential (CNP), sweet and easy to mash. Root flesh creamy-coloured with dry matter 29%. Does well in warm, semi-arid areas, 200–2000 m.a.s.l. with rainfall of 500–1000 mm/year. | D6: CASSAVA-1 | E6: Drought tolerance does not eliminate need for adequate moisture, Best for warm semi-arid areas, Requires validation in different regions, Sweet variety - good for fresh consumption, Early maturity helps escape drought | F6: drought tolerant, CMD resistant, early maturing, low cyanide, creamy flesh, semi-arid adaptation | G6: Validated
A7: 4 | B7: Cassava variety Katune (990005) (Cassava) | C7: Variety with creamy root flesh, maturing in 8–10 months, dry matter 36%, moderate yielder (37.1 t/ha), resistant to CMD and tolerant to CBSD, CBB, CGM and CMB. Adapted to 200–1500 m.a.s.l., rainfall of 500–1000 mm and temperatures of 24–27 °C. | D7: CASSAVA-1 | E7: High dry matter (36%) good for processing, Moderate yield potential, Adapted to wide altitude range, Requires well-drained soils, Monitor for disease resistance durability | F7: high dry matter, CMD resistant, multi-pest tolerant, creamy flesh, moderate yielder, wide adaptation | G7: Validated
A8: 5 | B8: Cassava variety KME-2 (Cassava) | C8: Drought tolerant, medium yielder (40 t/ha), resistant to CMD, early maturing with low cyanogenic potential (CNP), sweet and poundable. Root flesh creamy-coloured with dry matter 29%. Does well in warm, semi-arid areas, 200–2000 m.a.s.l. with rainfall of 500–1000 mm/year. | D8: CASSAVA-1 | E8: Drought tolerance varies with stress severity, Requires validation in target counties, Poundable quality good for processing, Sweet variety - low cyanide content, Best for semi-arid warm areas | F8: drought tolerant, CMD resistant, early maturing, low cyanide, poundable, semi-arid adaptation | G8: Validated
A9: 6 | B9: Cassava variety Mygera (Cassava) | C9: Mid-maturing, ready for harvest from 10–12 months, yields 20–43 t/ha, tolerant to CBSD, CBB, CMD, CMB and CGM. Sweet tasting (low cyanide 1.6–15.4 mg/100 g), dry matter 24–52.5%. Optimal conditions: 500–1200 mm rainfall, altitude 800–1750 m.a.s.l. | D9: CASSAVA-1 | E9: Wide yield range (20–43 t/ha) depends on management, Broad disease tolerance, Altitude range 800–1750 m.a.s.l., Sweet variety suitable for fresh consumption, Dry matter varies widely (24–52.5%) | F9: mid-maturing, disease tolerant, low cyanide, sweet tasting, variable dry matter, wide altitude adaptation | G9: Validated
A10: 7 | B10: Cassava variety Shibe (Cassava) | C10: High yielder (70 t/ha), medium maturing (8–12 months), resistant to CMD and tolerant to CBSD. Straight stems ideal for intercropping. Does well at altitudes of 15–1200 m.a.s.l., rainfall of 500–1000 mm and temperatures of 24–27 °C. | D10: CASSAVA-1 | E10: Very high yield potential requires good management, Straight stems good for intercropping, Low altitude adaptation (15–1200 m.a.s.l.), Requires validation in target counties, Seed availability limited | F10: high yielding, CMD resistant, CBSD tolerant, straight stems, intercropping ideal, low altitude | G10: Validated
A11: 8 | B11: Cassava variety Tajirika (Cassava) | C11: Early maturing variety (8 months after planting, MAP), high yield (63.3 t/ha), resistant to CMD and tolerant to CBSD. Straight stems allow for intercropping. Performs well at altitudes of 15–1200 m.a.s.l., rainfall of 500–1000 mm, well-drained sandy loam soils and temperatures of 24–27 °C. | D11: CASSAVA-1 | E11: Early maturity (8 months) good for food security, High yield requires good agronomic practices, Straight stems ideal for intercropping, Low altitude adaptation, Requires well-drained sandy loam soils | F11: early maturing, high yielding, CMD resistant, CBSD tolerant, straight stems, low altitude | G11: Validated
A12: 9 | B12: Cassava variety Nzalauka (Cassava) | C12: Resistant to CMD, tolerant to CBSD, straight stems ideal for intercropping, yields 52.9 t/ha, matures between 6–8 months. Optimal ecology: altitude 15–1200 m.a.s.l., temperature 24–27 °C and rainfall 500–1000 mm/year. | D12: CASSAVA-1 | E12: Very early maturity (6–8 months), High yield potential, Straight stems for intercropping, Low altitude adaptation, Requires validation in new areas | F12: very early maturing, high yielding, CMD resistant, CBSD tolerant, straight stems, low altitude | G12: Validated
A13: 10 | B13: Cassava variety Siri (Cassava) | C13: Resistant to CMD, tolerant to CBSD, high branching ideal for intercropping, matures between 8–12 months, yields 57.7 t/ha. Optimal ecology: 15–1200 m.a.s.l., rainfall 400–1000 mm/year, temperature 24–27 °C. | D13: CASSAVA-1 | E13: High branching suitable for intercropping, Moderate to high yield, Drought tolerant (400–1000 mm rainfall), Low altitude adaptation, Seed availability limited | F13: CMD resistant, CBSD tolerant, high branching, intercropping suitable, drought tolerant, low altitude | G13: Validated
A14: 11 | B14: Cassava variety Karibuni (Cassava) | C14: Resistant to CMD, matures in 8 months, yields 68.2 t/ha. Optimal environmental conditions: altitude 15–1200 m.a.s.l., rainfall 400–1000 mm/year, temperature 24–27 °C. | D14: CASSAVA-1 | E14: Very high yield potential, Early maturity (8 months), Drought tolerant, Requires validation in different agro-ecologies, Low altitude adaptation only | F14: high yielding, early maturing, CMD resistant, drought tolerant, low altitude, high potential | G14: Validated
A15: 12 | B15: Cassava variety Siri (Cassava) | C15: Resistant to CMD, tolerant to CBSD, very short and non-branching, matures between 8–12 months, yields 57.7 t/ha. Optimal ecology: altitude 15–1200 m.a.s.l., rainfall 400–1000 mm/year, temperature 24–27 °C. | D15: CASSAVA-1 | E15: Very short and non-branching - suitable for high density, Moderate to high yield, Drought tolerant, Good for intercropping, Low altitude adaptation | F15: CMD resistant, CBSD tolerant, non-branching, short stature, drought tolerant, low altitude | G15: Validated
... A41: 38 | B41: Business plans, Registration, branding and advertising (Cassava) | C41: Consumer-preferred identified products form the basis for developing business plans. Commercial villages or innovation platforms choose products with comparative advantage, register, brand and promote them. | D41: CASSAVA-1 | E41: Business planning requires skills training, Registration with KEBS required, Branding and advertising require investment, Commercial villages need capacity building, Sustainable market linkages essential | F41: business plans, registration, branding, advertising, commercialization, entrepreneurship | G41: Validated

Sheet Summary
B2: Screening Summary (live count)
B3: Updates automatically as each group screens and classifies its items.
B5: Group | C5: Total Items | D5: Ready to Certify | E5: Needs Review | F5: Needs Update | G5: High Risk
B6: Crop | C6: =COUNTA(Crop!C7) -> 1 | D6: =COUNTIF(Crop!S7,"Ready to Certify") -> 0 | E6: =COUNTIF(Crop!S7,"Needs Review") -> 0 | F6: =COUNTIF(Crop!S7,"Needs Update") -> 0 | G6: =COUNTIF(Crop!R7,"High") -> 0
B7: Livestock | C7: =COUNTA(#REF!) -> 1 | D7: =COUNTIF(#REF!,"Ready to Certify") -> #REF! | E7: =COUNTIF(#REF!,"Needs Review") -> #REF! | F7: =COUNTIF(#REF!,"Needs Update") -> #REF! | G7: =COUNTIF(#REF!,"High") -> #REF!
B8: Fisheries | C8: =COUNTA(#REF!) -> 1 | D8: =COUNTIF(#REF!,"Ready to Certify") -> #REF! | E8: =COUNTIF(#REF!,"Needs Review") -> #REF! | F8: =COUNTIF(#REF!,"Needs Update") -> #REF! | G8: =COUNTIF(#REF!,"High") -> #REF!
B9: Soil | C9: =COUNTA(#REF!) -> 1 | D9: =COUNTIF(#REF!,"Ready to Certify") -> #REF! | E9: =COUNTIF(#REF!,"Needs Review") -> #REF! | F9: =COUNTIF(#REF!,"Needs Update") -> #REF! | G9: =COUNTIF(#REF!,"High") -> #REF!
B10: Pest & Disease | C10: =COUNTA(#REF!) -> 1 | D10: =COUNTIF(#REF!,"Ready to Certify") -> #REF! | E10: =COUNTIF(#REF!,"Needs Review") -> #REF! | F10: =COUNTIF(#REF!,"Needs Update") -> #REF! | G10: =COUNTIF(#REF!,"High") -> #REF!
B11: TOTAL | C11: =SUM(C6:C10) -> 5 | D11: =SUM(D6:D10) -> #REF! | E11: =SUM(E6:E10) -> #REF! | F11: =SUM(F6:F10) -> #REF! | G11: =SUM(G6:G10) -> #REF!
